setup.cfg
setup.py
stretch_pass/__init__.py
stretch_pass/config.py
stretch_pass/consts.py
stretch_pass/log.py
stretch_pass/password_deriver.py
stretch_pass.egg-info/PKG-INFO
stretch_pass.egg-info/SOURCES.txt
stretch_pass.egg-info/dependency_links.txt
stretch_pass.egg-info/entry_points.txt
stretch_pass.egg-info/requires.txt
stretch_pass.egg-info/top_level.txt