Metadata-Version: 1.1
Name: stretch-pass
Version: 0.1.3
Summary: Derive high-entropy passwords from passphrases using a slow key derivation function (a.k.a. key stretching)
Home-page: https://github.com/cpascoe95/stretch-pass
Author: Charles Pascoe
Author-email: charles@cpascoe.co.uk
License: UNKNOWN
Download-URL: https://github.com/cpascoe95/stretch-pass/archive/v0.1.3.tar.gz
Keywords: password,passpharse,kdf,hash,stretch,stretching
Platform: UNKNOWN
Classifier: Development Status :: 4 - Beta
Classifier: Environment :: Console
Classifier: Natural Language :: English
Classifier: Programming Language :: Python :: 3 :: Only
Classifier: Programming Language :: Python :: 3.5
Classifier: Programming Language :: Python :: 3.6
Classifier: Topic :: Security
Classifier: Topic :: Security :: Cryptography
Classifier: Topic :: Utilities
